bbbctl.py
bbbctl-0.3.2.dist-info/licenses/LICENSE
bbbctl-0.3.2.dist-info/METADATA
bbbctl-0.3.2.dist-info/WHEEL
bbbctl-0.3.2.dist-info/entry_points.txt
bbbctl-0.3.2.dist-info/top_level.txt
bbbctl-0.3.2.dist-info/RECORD
