Metadata-Version: 2.4
Name: bbbctl
Version: 0.3.2
Summary: BigBlueButton API command-line client
Home-page: https://github.com/defnull/bbbctl
Author: Marcel Hellkamp
Author-email: marc@gsites.de
Project-URL: Bug Tracker, https://github.com/defnull/bbbctl/issues
Classifier: Programming Language :: Python :: 3
Classifier: License :: OSI Approved :: MIT License
Classifier: Operating System :: OS Independent
Requires-Python: >=3.6
License-File: LICENSE
Dynamic: license-file
